dewland_stat_distributions/__init__.py
td_first/Binomialdistribution.py
td_first/Gaussiandistribution.py
td_first/Generaldistribution.py
td_first/__init__.py
td_first-0.1.dist-info/DESCRIPTION.rst
td_first-0.1.dist-info/METADATA
td_first-0.1.dist-info/RECORD
td_first-0.1.dist-info/WHEEL
td_first-0.1.dist-info/metadata.json
td_first-0.1.dist-info/top_level.txt
