Metadata-Version: 2.0
Name: td-first
Version: 0.1
Summary: Gaussian distributions
Home-page: UNKNOWN
Author: Tanya Dewland
Author-email: tanya.dewland@gmail.com
License: MIT
Platform: UNKNOWN
